{
  "generator-jhipster": {
    "promptValues": {
      "packageName": "com.everteam",
      "nativeLanguage": "en"
    },
    "jhipsterVersion": "5.7.0",
    "applicationType": "monolith",
    "baseName": "foot",
    "packageName": "com.everteam",
    "packageFolder": "com/everteam",
    "serverPort": "8080",
    "authenticationType": "session",
    "cacheProvider": "ehcache",
    "enableHibernateCache": true,
    "websocket": false,
    "databaseType": "sql",
    "devDatabaseType": "postgresql",
    "prodDatabaseType": "postgresql",
    "searchEngine": false,
    "messageBroker": false,
    "serviceDiscoveryType": false,
    "buildTool": "maven",
    "enableSwaggerCodegen": false,
    "rememberMeKey": "8ed77ba3a37fd7041c1b3f9830d8102fb68726a201fcf54b9868aeb37cd7159b32e79cc30b3795cd0afc70944d19849fe437",
    "clientFramework": "angularX",
    "useSass": true,
    "clientPackageManager": "npm",
    "testFrameworks": [],
    "jhiPrefix": "jhi",
    "otherModules": [],
    "enableTranslation": true,
    "nativeLanguage": "en",
    "languages": [
      "en"
    ]
  }
}